{"version":3,"kind":"Article","sha256":"864f3d8a33e03cf27dea31772ca97d7499c95e15dc4188c6bc33490d15cdc89e","slug":"index","location":"/intro_microcredential_UCLM.md","dependencies":[],"frontmatter":{"title":"IA y Tecnologías Geoespaciales Aplicadas a la Restauración de Ecosistemas Forestales Afectados por Incendios y Sequías Extremas","content_includes_title":false,"authors":[{"nameParsed":{"literal":"Benjamin Mary","given":"Benjamin","family":"Mary"},"name":"Benjamin Mary","orcid":"0000-0000-0000-0000","corresponding":true,"email":"benjamin.mary@ica.csic.es","affiliations":["uni"],"id":"contributors-myst-generated-uid-0"}],"date":"2025-01-19","doi":"10.5281/zenodo.0000000","license":{"content":{"id":"CC-BY-4.0","url":"https://creativecommons.org/licenses/by/4.0/","name":"Creative Commons Attribution 4.0 International","free":true,"CC":true},"code":{"id":"MIT","url":"https://opensource.org/licenses/MIT","name":"MIT License","free":true,"osi":true}},"github":"https://github.com/BenjMy/geophysics_postfire_book-jb2","binder":"https://mybinder.org/v2/gh/BenjMy/geophysics_postfire_book-jb2/main","keywords":["geophysics","electrical resistivity tomography","electromagnetic induction","python","resipy","emagpy","open education"],"copyright":"2025","affiliations":[{"id":"uni","name":"CSIC","department":"ICA","city":"Madrid","country":"Spain"}],"settings":{"output_stderr":"show"},"source_url":"https://github.com/BenjMy/geophysics_postfire_book-jb2/blob/main/intro_microcredential_UCLM.md","edit_url":"https://github.com/BenjMy/geophysics_postfire_book-jb2/edit/main/intro_microcredential_UCLM.md","thumbnail":"/micro_UCLM_flyer-e05b06d6245c1e2bc6cbcc820ee33162.jpeg","exports":[{"format":"md","filename":"intro_microcredential_UCLM.md","url":"/intro_microcredentia-42384def0daf7fa7b5a62f4e8dde3fc8.md"}]},"mdast":{"type":"root","children":[{"type":"block","children":[{"type":"thematicBreak","position":{"start":{"line":3,"column":1},"end":{"line":3,"column":1}},"key":"U2wNLwabFx"},{"type":"heading","depth":2,"position":{"start":{"line":5,"column":1},"end":{"line":5,"column":1}},"children":[{"type":"text","value":"GRWater Project","position":{"start":{"line":5,"column":1},"end":{"line":5,"column":1}},"key":"tA9ijBW3HF"}],"identifier":"grwater-project","label":"GRWater Project","html_id":"grwater-project","implicit":true,"key":"oirFbaMzs2"},{"type":"paragraph","position":{"start":{"line":7,"column":1},"end":{"line":7,"column":1}},"children":[{"type":"text","value":"Multi-scale monitoring of the Earth Critical Zone — a key, missing parameter for assessing forest post-fire management in the face of global warming.","position":{"start":{"line":7,"column":1},"end":{"line":7,"column":1}},"key":"sRejSn0ign"}],"key":"uPz4EtwC5R"},{"type":"paragraph","position":{"start":{"line":9,"column":1},"end":{"line":10,"column":1}},"children":[{"type":"text","value":"To follow news and the latest scientific developments visit the\n","position":{"start":{"line":9,"column":1},"end":{"line":9,"column":1}},"key":"gXyfR5YQQA"},{"type":"link","url":"https://grwater.ica.csic.es/","position":{"start":{"line":9,"column":1},"end":{"line":9,"column":1}},"children":[{"type":"text","value":"GRWATER web portal","position":{"start":{"line":9,"column":1},"end":{"line":9,"column":1}},"key":"r6GrhcfI8M"}],"urlSource":"https://grwater.ica.csic.es/","key":"NKYRWDBfYQ"},{"type":"text","value":".","position":{"start":{"line":9,"column":1},"end":{"line":9,"column":1}},"key":"CNS1hWLn6V"}],"key":"DpwugGLcit"},{"type":"thematicBreak","position":{"start":{"line":12,"column":1},"end":{"line":12,"column":1}},"key":"GmfG5LbCAl"},{"type":"admonition","children":[{"type":"admonitionTitle","children":[{"type":"text","value":"Contact","position":{"start":{"line":14,"column":1},"end":{"line":14,"column":1}},"key":"muXlYRVUY2"}],"key":"qnhI91huqM"},{"type":"paragraph","position":{"start":{"line":16,"column":1},"end":{"line":16,"column":1}},"children":[{"type":"strong","position":{"start":{"line":16,"column":1},"end":{"line":16,"column":1}},"children":[{"type":"text","value":"Benjamin Mary","position":{"start":{"line":16,"column":1},"end":{"line":16,"column":1}},"key":"y02kqVisnM"}],"key":"Yv6ZBp1VnW"},{"type":"text","value":" — ","position":{"start":{"line":16,"column":1},"end":{"line":16,"column":1}},"key":"f6AUvhuc1y"},{"type":"link","url":"mailto:benjamin.mary@ica.csic.es","position":{"start":{"line":16,"column":1},"end":{"line":16,"column":1}},"children":[{"type":"text","value":"benjamin​.mary@ica​.csic​.es","position":{"start":{"line":16,"column":1},"end":{"line":16,"column":1}},"key":"osAL9hf07A"}],"urlSource":"mailto:benjamin.mary@ica.csic.es","key":"iMIBqqIQx7"}],"key":"U8CQp5efoW"}],"class":"tip","key":"EgtCzB0FvV"},{"type":"admonition","children":[{"type":"admonitionTitle","children":[{"type":"text","value":"Important note","position":{"start":{"line":19,"column":1},"end":{"line":19,"column":1}},"key":"GRUZAAZD23"}],"key":"kaNUpxTObo"},{"type":"comment","value":" TODO: add the important note content here ","key":"zkDr895o2e"}],"class":"warning","key":"PcNHVSFWJA"},{"type":"admonition","children":[{"type":"admonitionTitle","children":[{"type":"text","value":"Data Acquisition & Processing Service","position":{"start":{"line":24,"column":1},"end":{"line":24,"column":1}},"key":"WaMfMYug3F"}],"key":"DDeRC52wsc"},{"type":"paragraph","position":{"start":{"line":26,"column":1},"end":{"line":29,"column":1}},"children":[{"type":"link","url":"https://www.ica.csic.es","position":{"start":{"line":26,"column":1},"end":{"line":26,"column":1}},"children":[{"type":"text","value":"ICA-CSIC","position":{"start":{"line":26,"column":1},"end":{"line":26,"column":1}},"key":"gShjOKhKbC"}],"urlSource":"https://www.ica.csic.es","key":"ZxdjlZwCSO"},{"type":"text","value":" offers a professional service for geophysical\ndata acquisition and processing as part of its\n","position":{"start":{"line":26,"column":1},"end":{"line":26,"column":1}},"key":"UvYQPvULTc"},{"type":"link","url":"https://www.ica.csic.es/servicios/servicios-cientifico-tecnicos/tecnologias-geo-espaciales-para-el-estudio-de-sistemas-agro-forestales","position":{"start":{"line":26,"column":1},"end":{"line":26,"column":1}},"children":[{"type":"text","value":"Geo-Spatial Technologies for Agro-Forestry Systems","position":{"start":{"line":26,"column":1},"end":{"line":26,"column":1}},"key":"hXhEFanVgD"}],"urlSource":"https://www.ica.csic.es/servicios/servicios-cientifico-tecnicos/tecnologias-geo-espaciales-para-el-estudio-de-sistemas-agro-forestales","key":"gpZWjTu4fk"},{"type":"text","value":"\nscientific-technical services unit.","position":{"start":{"line":26,"column":1},"end":{"line":26,"column":1}},"key":"YKU6NYyG4T"}],"key":"DDcHiIgd2p"}],"class":"note","key":"Hoi7TocuMl"},{"type":"thematicBreak","position":{"start":{"line":32,"column":1},"end":{"line":32,"column":1}},"key":"wWtdAL7Ncr"},{"type":"image","url":"/micro_UCLM_flyer-e05b06d6245c1e2bc6cbcc820ee33162.jpeg","alt":"Micro UCLM flyer","width":"30%","align":"center","key":"TfZt1sbvu9","urlSource":"assets/images/micro_UCLM_flyer.jpeg"}],"key":"aeg5uxfbNa"}],"key":"K5taA8xlCr"},"references":{"cite":{"order":[],"data":{}}}}