{"version":3,"kind":"Article","sha256":"fd3fa307b9335bb8d7db5728058ab23e83ae6a7b3c484c4959182ab88d9a33f6","slug":"readme","location":"/exercises/README.md","dependencies":[],"frontmatter":{"title":"Course Exercises","authors":[{"nameParsed":{"literal":"Benjamin Mary","given":"Benjamin","family":"Mary"},"name":"Benjamin Mary","orcid":"0000-0000-0000-0000","corresponding":true,"email":"benjamin.mary@ica.csic.es","affiliations":["uni"],"id":"contributors-myst-generated-uid-0"}],"date":"2025-01-19","doi":"10.5281/zenodo.0000000","license":{"content":{"id":"CC-BY-4.0","url":"https://creativecommons.org/licenses/by/4.0/","name":"Creative Commons Attribution 4.0 International","free":true,"CC":true},"code":{"id":"MIT","url":"https://opensource.org/licenses/MIT","name":"MIT License","free":true,"osi":true}},"github":"https://github.com/BenjMy/geophysics_postfire_book-jb2","binder":"https://mybinder.org/v2/gh/BenjMy/geophysics_postfire_book-jb2/main","keywords":["geophysics","electrical resistivity tomography","electromagnetic induction","python","resipy","emagpy","open education"],"copyright":"2025","affiliations":[{"id":"uni","name":"CSIC","department":"ICA","city":"Madrid","country":"Spain"}],"settings":{"output_stderr":"show"},"numbering":{"title":{"offset":1}},"source_url":"https://github.com/BenjMy/geophysics_postfire_book-jb2/blob/main/exercises/README.md","edit_url":"https://github.com/BenjMy/geophysics_postfire_book-jb2/edit/main/exercises/README.md","exports":[{"format":"md","filename":"README.md","url":"/README-c2fef9e115ebe03f8de8b32dc224ede2.md"}]},"mdast":{"type":"root","children":[{"type":"block","children":[{"type":"heading","depth":2,"position":{"start":{"line":6,"column":1},"end":{"line":6,"column":1}},"children":[{"type":"text","value":"Course exercises overview","position":{"start":{"line":6,"column":1},"end":{"line":6,"column":1}},"key":"KDfdvqGzOD"}],"identifier":"course-exercises-overview","label":"Course exercises overview","html_id":"course-exercises-overview","implicit":true,"key":"mx6KjgfIH9"},{"type":"admonition","children":[{"type":"admonitionTitle","children":[{"type":"text","value":"Golden rule","position":{"start":{"line":8,"column":1},"end":{"line":8,"column":1}},"key":"WBNAq5Ulx3"}],"key":"YrkhnGLayd"},{"type":"paragraph","position":{"start":{"line":10,"column":1},"end":{"line":10,"column":1}},"children":[{"type":"text","value":"Always ","position":{"start":{"line":10,"column":1},"end":{"line":10,"column":1}},"key":"rwgZJzDE7t"},{"type":"strong","position":{"start":{"line":10,"column":1},"end":{"line":10,"column":1}},"children":[{"type":"text","value":"attempt the exercise yourself","position":{"start":{"line":10,"column":1},"end":{"line":10,"column":1}},"key":"WEwFiMr7Lg"}],"key":"Chc6KE7RkW"},{"type":"text","value":" before looking at the solution. Struggling with a problem is where learning happens!","position":{"start":{"line":10,"column":1},"end":{"line":10,"column":1}},"key":"jCjTf3ifGg"}],"key":"iAfUOJv7zM"}],"class":"important","key":"rn9gQ9hxkX"},{"type":"thematicBreak","position":{"start":{"line":13,"column":1},"end":{"line":13,"column":1}},"key":"nrwbndi3Lu"},{"type":"thematicBreak","position":{"start":{"line":15,"column":1},"end":{"line":15,"column":1}},"key":"ls6iSzhViJ"},{"type":"heading","depth":3,"position":{"start":{"line":16,"column":1},"end":{"line":16,"column":1}},"children":[{"type":"text","value":"Topics","position":{"start":{"line":16,"column":1},"end":{"line":16,"column":1}},"key":"sZDo1pWLKg"}],"identifier":"topics","label":"Topics","html_id":"topics","implicit":true,"key":"y3rewlJ17O"},{"type":"grid","columns":[1,1,2,2],"children":[{"type":"card","children":[{"type":"cardTitle","children":[{"type":"strong","position":{"start":{"line":21,"column":1},"end":{"line":21,"column":1}},"children":[{"type":"text","value":"Exercice 1","position":{"start":{"line":21,"column":1},"end":{"line":21,"column":1}},"key":"E1lxuyDbWP"}],"key":"CV92YnvPG7"},{"type":"text","value":" ⁉️ ","position":{"start":{"line":21,"column":1},"end":{"line":21,"column":1}},"key":"hZmibEWiDC"},{"type":"link","url":"/exercice1-resistivitybasics","position":{"start":{"line":21,"column":1},"end":{"line":21,"column":1}},"children":[{"type":"text","value":"Understanding Resistivity Basics","position":{"start":{"line":21,"column":1},"end":{"line":21,"column":1}},"key":"GQBeDuSNcr"}],"urlSource":"Exercice1_ResistivityBasics.md","dataUrl":"/exercice1-resistivitybasics.json","internal":true,"protocol":"file","key":"pZo7yvdg5f"}],"key":"CfJVD4YBm1"},{"type":"paragraph","position":{"start":{"line":24,"column":1},"end":{"line":24,"column":1}},"children":[{"type":"text","value":"Understand how resistivity varies with material type and moisture content.","position":{"start":{"line":24,"column":1},"end":{"line":24,"column":1}},"key":"AyZuIEH9NW"}],"key":"Pb6FwB11St"},{"type":"paragraph","position":{"start":{"line":26,"column":1},"end":{"line":26,"column":1}},"children":[{"type":"strong","position":{"start":{"line":26,"column":1},"end":{"line":26,"column":1}},"children":[{"type":"text","value":"Discussion:","position":{"start":{"line":26,"column":1},"end":{"line":26,"column":1}},"key":"HuMt1o4U3U"}],"key":"Voxfv0sqHy"}],"key":"IHDRvAszM4"},{"type":"list","ordered":false,"spread":false,"position":{"start":{"line":27,"column":1},"end":{"line":28,"column":1}},"children":[{"type":"listItem","spread":true,"position":{"start":{"line":27,"column":1},"end":{"line":27,"column":1}},"children":[{"type":"paragraph","children":[{"type":"text","value":"Why does moisture content affect resistivity?","position":{"start":{"line":27,"column":1},"end":{"line":27,"column":1}},"key":"OO1Ypex1lo"}],"key":"L6Pb0kjK4u"}],"key":"y7EysfTidY"},{"type":"listItem","spread":true,"position":{"start":{"line":28,"column":1},"end":{"line":28,"column":1}},"children":[{"type":"paragraph","children":[{"type":"text","value":"How might this impact ERT surveys?","position":{"start":{"line":28,"column":1},"end":{"line":28,"column":1}},"key":"Jr42UZwcZM"}],"key":"ytl2mAC8jL"}],"key":"WEIILyK2Qu"}],"key":"Po1ZfeR783"}],"key":"nJgZm9o0yL"},{"type":"card","children":[{"type":"cardTitle","children":[{"type":"strong","position":{"start":{"line":31,"column":1},"end":{"line":31,"column":1}},"children":[{"type":"text","value":"Exercice 2","position":{"start":{"line":31,"column":1},"end":{"line":31,"column":1}},"key":"uLbb4Xbcar"}],"key":"klytRML4Hx"},{"type":"text","value":" ⁉️ ","position":{"start":{"line":31,"column":1},"end":{"line":31,"column":1}},"key":"aQ0gJSxWO8"},{"type":"link","url":"/exercice2-ertsurveydesign","position":{"start":{"line":31,"column":1},"end":{"line":31,"column":1}},"children":[{"type":"text","value":"ERT Survey Design","position":{"start":{"line":31,"column":1},"end":{"line":31,"column":1}},"key":"wzbcUUAbYG"}],"urlSource":"Exercice2_ERTSurveyDesign.md","dataUrl":"/exercice2-ertsurveydesign.json","internal":true,"protocol":"file","key":"bdFJwCbyBN"}],"key":"N1qbFseTxY"},{"type":"paragraph","position":{"start":{"line":34,"column":1},"end":{"line":34,"column":1}},"children":[{"type":"text","value":"Design an ERT survey for a given scenario, including electrode spacing, profile length, and acquisition sequence.","position":{"start":{"line":34,"column":1},"end":{"line":34,"column":1}},"key":"KGfAbJhccZ"}],"key":"si1Ejoe0ap"}],"key":"TmbuAW02gY"},{"type":"card","children":[{"type":"cardTitle","children":[{"type":"strong","position":{"start":{"line":38,"column":1},"end":{"line":38,"column":1}},"children":[{"type":"text","value":"Exercice 3","position":{"start":{"line":38,"column":1},"end":{"line":38,"column":1}},"key":"XGKf6YjuqQ"}],"key":"vucAo1fCjl"},{"type":"text","value":" ⁉️ ","position":{"start":{"line":38,"column":1},"end":{"line":38,"column":1}},"key":"E5FUfS1ts2"},{"type":"link","url":"/exercice3-fielddataanalysis","position":{"start":{"line":38,"column":1},"end":{"line":38,"column":1}},"children":[{"type":"text","value":"Field Data Analysis","position":{"start":{"line":38,"column":1},"end":{"line":38,"column":1}},"key":"k67KPsm17h"}],"urlSource":"Exercice3_FieldDataAnalysis.md","dataUrl":"/exercice3-fielddataanalysis.json","internal":true,"protocol":"file","key":"bmkbJxuG6h"}],"key":"KgvdkgYsET"},{"type":"paragraph","position":{"start":{"line":41,"column":1},"end":{"line":41,"column":1}},"children":[{"type":"text","value":"Analyze real or synthetic field data from both ERT and EM surveys, including inversion.","position":{"start":{"line":41,"column":1},"end":{"line":41,"column":1}},"key":"CxjUW9Sxx6"}],"key":"RB3hW8q58j"}],"key":"oixmzvrcp2"},{"type":"card","children":[{"type":"cardTitle","children":[{"type":"strong","position":{"start":{"line":45,"column":1},"end":{"line":45,"column":1}},"children":[{"type":"text","value":"Exercice 4","position":{"start":{"line":45,"column":1},"end":{"line":45,"column":1}},"key":"j9IjDLEx9Z"}],"key":"UhbfIIshyp"},{"type":"text","value":" ⁉️ ","position":{"start":{"line":45,"column":1},"end":{"line":45,"column":1}},"key":"S3hkdYWAJa"},{"type":"link","url":"/exercice4-fielddatainterpretation","position":{"start":{"line":45,"column":1},"end":{"line":45,"column":1}},"children":[{"type":"text","value":"Field Data Analysis","position":{"start":{"line":45,"column":1},"end":{"line":45,"column":1}},"key":"DS9o1dc9Xa"}],"urlSource":"Exercice4_FieldDataInterpretation.md","dataUrl":"/exercice4-fielddatainterpretation.json","internal":true,"protocol":"file","key":"CtDpisD9eP"}],"key":"c5GmJVvAUt"},{"type":"paragraph","position":{"start":{"line":48,"column":1},"end":{"line":48,"column":1}},"children":[{"type":"text","value":"Analyze real data and make the interpretation.","position":{"start":{"line":48,"column":1},"end":{"line":48,"column":1}},"key":"iYbcOO6JHK"}],"key":"k1M6nzIG87"}],"key":"AjYbSQj4Nq"}],"key":"JCsWmHioR7"},{"type":"thematicBreak","position":{"start":{"line":53,"column":1},"end":{"line":53,"column":1}},"key":"OLrUyw9Dsj"},{"type":"heading","depth":3,"position":{"start":{"line":56,"column":1},"end":{"line":56,"column":1}},"children":[{"type":"text","value":"Further Reading","position":{"start":{"line":56,"column":1},"end":{"line":56,"column":1}},"key":"Ec5kQk4Rx7"}],"identifier":"further-reading","label":"Further Reading","html_id":"further-reading","implicit":true,"key":"eh7tLYs9Jx"},{"type":"list","ordered":false,"spread":false,"position":{"start":{"line":58,"column":1},"end":{"line":62,"column":1}},"children":[{"type":"listItem","spread":true,"position":{"start":{"line":58,"column":1},"end":{"line":58,"column":1}},"children":[{"type":"paragraph","children":[{"type":"link","url":"https://resipy.readthedocs.io/","position":{"start":{"line":58,"column":1},"end":{"line":58,"column":1}},"children":[{"type":"text","value":"resipy documentation","position":{"start":{"line":58,"column":1},"end":{"line":58,"column":1}},"key":"DVamiBaVwZ"}],"urlSource":"https://resipy.readthedocs.io/","key":"CEW78aeICI"}],"key":"HZRmNKX2eY"}],"key":"r25aaiCVu7"},{"type":"listItem","spread":true,"position":{"start":{"line":59,"column":1},"end":{"line":59,"column":1}},"children":[{"type":"paragraph","children":[{"type":"link","url":"https://www.pygimli.org/","position":{"start":{"line":59,"column":1},"end":{"line":59,"column":1}},"children":[{"type":"text","value":"PyGimli: ERT and EM inversion","position":{"start":{"line":59,"column":1},"end":{"line":59,"column":1}},"key":"L3KjXEsSGF"}],"urlSource":"https://www.pygimli.org/","key":"UjnBebDrW8"}],"key":"PjiXVZqmTt"}],"key":"ZPbp0OzXiM"},{"type":"listItem","spread":true,"position":{"start":{"line":60,"column":1},"end":{"line":62,"column":1}},"children":[{"type":"paragraph","children":[{"type":"link","url":"https://www.geometrics.com/","position":{"start":{"line":60,"column":1},"end":{"line":60,"column":1}},"children":[{"type":"text","value":"EM Survey Guidelines","position":{"start":{"line":60,"column":1},"end":{"line":60,"column":1}},"key":"i4NRWUHIWY"}],"urlSource":"https://www.geometrics.com/","key":"hGqgOPciJ2"}],"key":"qSNI0O4cwo"}],"key":"Rytdm9MV3B"}],"key":"t15v0sh3JJ"},{"type":"heading","depth":3,"position":{"start":{"line":63,"column":1},"end":{"line":63,"column":1}},"children":[{"type":"text","value":"Structure","position":{"start":{"line":63,"column":1},"end":{"line":63,"column":1}},"key":"swcT3zkh1J"}],"identifier":"structure","label":"Structure","html_id":"structure","implicit":true,"key":"AScIq2Gtrq"},{"type":"paragraph","position":{"start":{"line":65,"column":1},"end":{"line":65,"column":1}},"children":[{"type":"text","value":"Each week’s exercise folder contains:","position":{"start":{"line":65,"column":1},"end":{"line":65,"column":1}},"key":"KdINXSCBUE"}],"key":"XDIgIR5Li2"},{"type":"list","ordered":false,"spread":false,"position":{"start":{"line":67,"column":1},"end":{"line":69,"column":1}},"children":[{"type":"listItem","spread":true,"position":{"start":{"line":67,"column":1},"end":{"line":67,"column":1}},"children":[{"type":"paragraph","children":[{"type":"strong","position":{"start":{"line":67,"column":1},"end":{"line":67,"column":1}},"children":[{"type":"text","value":"Main exercise notebook","position":{"start":{"line":67,"column":1},"end":{"line":67,"column":1}},"key":"R7n82DdjK1"}],"key":"Cb6N56nCga"},{"type":"text","value":" — problems with guidance and hints","position":{"start":{"line":67,"column":1},"end":{"line":67,"column":1}},"key":"Ny9q8rNTFS"}],"key":"XvB2EirIEZ"}],"key":"R6JfkCVyFV"},{"type":"listItem","spread":true,"position":{"start":{"line":68,"column":1},"end":{"line":69,"column":1}},"children":[{"type":"paragraph","children":[{"type":"strong","position":{"start":{"line":68,"column":1},"end":{"line":68,"column":1}},"children":[{"type":"inlineCode","value":"solutions/","position":{"start":{"line":68,"column":1},"end":{"line":68,"column":1}},"key":"fz0TUaXDEe"},{"type":"text","value":" sub-folder","position":{"start":{"line":68,"column":1},"end":{"line":68,"column":1}},"key":"rNuE5H2LPw"}],"key":"BKgPvGPZwL"},{"type":"text","value":" — reference implementations to review after your attempt","position":{"start":{"line":68,"column":1},"end":{"line":68,"column":1}},"key":"tErrBtM3ap"}],"key":"J3gbf05FTl"}],"key":"oEZBlvv0rF"}],"key":"vJRP6JSpIO"},{"type":"code","lang":"","value":"exercises/\n├── exercice1/\n│   ├── exercise1.md\n│   └── solutions/\n│       └── exercise1.md\n├── exercice2/\n│   ├── exercise2.md\n│   └── solutions/\n│       └── exercise2.md","position":{"start":{"line":70,"column":1},"end":{"line":80,"column":1}},"key":"coweSKEoop"},{"type":"heading","depth":3,"position":{"start":{"line":84,"column":1},"end":{"line":84,"column":1}},"children":[{"type":"text","value":"Guidelines","position":{"start":{"line":84,"column":1},"end":{"line":84,"column":1}},"key":"xPL3VuygUI"}],"identifier":"guidelines","label":"Guidelines","html_id":"guidelines","implicit":true,"key":"HYPfHtuKcu"},{"type":"container","kind":"table","children":[{"type":"table","children":[{"type":"tableRow","children":[{"type":"tableCell","header":true,"children":[{"type":"heading","depth":2,"position":{"start":{"line":90,"column":1},"end":{"line":90,"column":1}},"children":[],"key":"zL2OMGY5N8"}],"key":"LFglIp4XUd"},{"type":"tableCell","header":true,"children":[{"type":"paragraph","children":[{"type":"text","value":"Guideline","position":{"start":{"line":91,"column":1},"end":{"line":91,"column":1}},"key":"lK6tf4zPPb"}],"key":"W4QVW88Vvn"}],"key":"kvh3diikwk"}],"key":"kHpTY1FVZK"},{"type":"tableRow","children":[{"type":"tableCell","children":[{"type":"paragraph","children":[{"type":"text","value":"1","position":{"start":{"line":92,"column":1},"end":{"line":92,"column":1}},"key":"lJ7NMHaOpn"}],"key":"Vxb7XYkJgm"}],"key":"uyT6myIDLr"},{"type":"tableCell","children":[{"type":"paragraph","children":[{"type":"text","value":"Attempt exercises ","position":{"start":{"line":93,"column":1},"end":{"line":93,"column":1}},"key":"xrq5YhPdpi"},{"type":"strong","position":{"start":{"line":93,"column":1},"end":{"line":93,"column":1}},"children":[{"type":"text","value":"before","position":{"start":{"line":93,"column":1},"end":{"line":93,"column":1}},"key":"nRAX4Ov8Jm"}],"key":"pjCAnDo7Wn"},{"type":"text","value":" viewing solutions","position":{"start":{"line":93,"column":1},"end":{"line":93,"column":1}},"key":"HRYvdi45UM"}],"key":"dDAXIwKJGa"}],"key":"t5NJ1pQ10E"}],"key":"qKtFPmkXbI"},{"type":"tableRow","children":[{"type":"tableCell","children":[{"type":"paragraph","children":[{"type":"text","value":"2","position":{"start":{"line":94,"column":1},"end":{"line":94,"column":1}},"key":"ckfyizLzli"}],"key":"lKPdLDVMBC"}],"key":"I5OjUUjYEJ"},{"type":"tableCell","children":[{"type":"paragraph","children":[{"type":"text","value":"Experiment — change parameters and observe what happens","position":{"start":{"line":95,"column":1},"end":{"line":95,"column":1}},"key":"LXNBhBLi9x"}],"key":"OU35G36LoV"}],"key":"hT4ipB7DC8"}],"key":"fcBA9D621S"},{"type":"tableRow","children":[{"type":"tableCell","children":[{"type":"paragraph","children":[{"type":"text","value":"3","position":{"start":{"line":96,"column":1},"end":{"line":96,"column":1}},"key":"hdaDnfPfRR"}],"key":"gl6wn04teU"}],"key":"a0Txwr9Yai"},{"type":"tableCell","children":[{"type":"paragraph","children":[{"type":"text","value":"Compare your approach with the provided solution; both can be correct!","position":{"start":{"line":97,"column":1},"end":{"line":97,"column":1}},"key":"Ap8Cpl1npe"}],"key":"aAGF2vepep"}],"key":"Ops8NX2G7H"}],"key":"dT2DcC6y46"},{"type":"tableRow","children":[{"type":"tableCell","children":[{"type":"paragraph","children":[{"type":"text","value":"4","position":{"start":{"line":98,"column":1},"end":{"line":98,"column":1}},"key":"Hy6brf2ppu"}],"key":"coq1plG0zN"}],"key":"EAPYsZBWBr"},{"type":"tableCell","children":[{"type":"paragraph","children":[{"type":"text","value":"Ask questions in the course discussion if you are stuck for more than 20 minutes","position":{"start":{"line":99,"column":1},"end":{"line":99,"column":1}},"key":"ZkN2qRCzhT"}],"key":"bnczTn93UA"}],"key":"lno2DV2FoU"}],"key":"S8C17S5k1d"}],"key":"o1Km1g3a8C"}],"enumerator":"1","key":"ZVVXR7baCe"}],"key":"rK2XKYkiN3"}],"key":"TJBaz2EQJN"},"references":{"cite":{"order":[],"data":{}}}}